{
  "version": 1,
  "skills": [
    {
      "id": "agent-team",
      "label": "Agent team",
      "description": "Folder: agent-team",
      "sourceBranch": "agent-skills",
      "sourcePath": "agent-team"
    },
    {
      "id": "bugfix",
      "label": "Bugfix",
      "description": "Folder: bugfix",
      "sourceBranch": "agent-skills",
      "sourcePath": "bugfix"
    },
    {
      "id": "trace-bug",
      "label": "Trace bug",
      "description": "Folder: trace-bug",
      "sourceBranch": "agent-skills",
      "sourcePath": "trace-bug"
    },
    {
      "id": "business-analyst",
      "label": "Business analyst",
      "description": "Folder: business-analyst",
      "sourceBranch": "agent-skills",
      "sourcePath": "business-analyst"
    },
    {
      "id": "git-engineering-workflow",
      "label": "Git engineering workflow",
      "description": "Folder: git-engineering-workflow",
      "sourceBranch": "agent-skills",
      "sourcePath": "git-engineering-workflow"
    },
    {
      "id": "review-code",
      "label": "Review code",
      "description": "Folder: review-code",
      "sourceBranch": "agent-skills",
      "sourcePath": "review-code"
    },
    {
      "id": "cc-team-mini",
      "label": "CC Team Mini",
      "description": "Folder: cc-team-mini",
      "sourceBranch": "agent-skills",
      "sourcePath": "cc-team-mini"
    },
    {
      "id": "cc-team-full",
      "label": "CC Team Full",
      "description": "Folder: cc-team-full",
      "sourceBranch": "agent-skills",
      "sourcePath": "cc-team-full"
    }
  ]
}
